codoff/__init__.py
codoff/codoff.py
codoff/util.py
codoff-1.2.3.data/scripts/antismash_codoff
codoff-1.2.3.data/scripts/codoff
codoff-1.2.3.dist-info/licenses/LICENSE
codoff-1.2.3.dist-info/METADATA
codoff-1.2.3.dist-info/WHEEL
codoff-1.2.3.dist-info/top_level.txt
codoff-1.2.3.dist-info/RECORD
