Metadata-Version: 2.4
Name: codoff
Version: 1.2.3
Summary: Program to measure the irregularity of the codon usage for a single genomic region (e.g. a BGC, phage, etc.) relative to the full genome.
Author-email: Rauf Salamzade <salamzader@gmail.com>
License-File: LICENSE
Requires-Dist: setuptools
Requires-Dist: scipy
Requires-Dist: biopython
Requires-Dist: seaborn
Requires-Dist: matplotlib
Requires-Dist: pyrodigal
Dynamic: license-file
